tests/__init__.py
tests/test_mitre_data.py
ttpnav/__init__.py
ttpnav/mitre_data.py
ttpnav-0.1.4.dist-info/LICENSE
ttpnav-0.1.4.dist-info/METADATA
ttpnav-0.1.4.dist-info/WHEEL
ttpnav-0.1.4.dist-info/top_level.txt
ttpnav-0.1.4.dist-info/RECORD
