Metadata-Version: 2.1
Name: ttpnav
Version: 0.1.4
Summary: A package to navigate MITRE ATT&CK data easily.
Home-page: https://github.com/fish-not-phish/ttpnav
Author: Joseph Fisher
Author-email: jfisher@cyntel.com
Classifier: Programming Language :: Python :: 3
Classifier: License :: OSI Approved :: MIT License
Classifier: Operating System :: OS Independent
Requires-Python: >=3.6
License-File: LICENSE
Requires-Dist: mitreattack-python
